querystream.py
setup.py
querystream.egg-info/PKG-INFO
querystream.egg-info/SOURCES.txt
querystream.egg-info/dependency_links.txt
querystream.egg-info/top_level.txt