Metadata-Version: 1.1
Name: querystream
Version: 0.0.3
Summary: Offline implementation of the Django QuerySet.
Home-page: http://github.com/pstiasny/querystream
Author: Paweł Stiasny
Author-email: pawelstiasny@gmail.com
License: MIT
Keywords: django
Platform: UNKNOWN
Classifier: Intended Audience :: Developers
Classifier: License :: OSI Approved :: MIT License
Classifier: Operating System :: OS Independent
Classifier: Topic :: Database
Classifier: Programming Language :: Python :: 2
Classifier: Programming Language :: Python :: 2.7
